fakedcm/__init__.py
fakedcm/fakedcm.py
fakerdcm-1.0.0.dist-info/METADATA
fakerdcm-1.0.0.dist-info/WHEEL
fakerdcm-1.0.0.dist-info/entry_points.txt
fakerdcm-1.0.0.dist-info/top_level.txt
fakerdcm-1.0.0.dist-info/RECORD
